{
  "books": [
    {
      "title": "흑집사 31권",
      "link": "https://ridibooks.com/books/505055934?_rdt_sid=new-release&_rdt_idx=0",
      "author": "토보소 야나",
      "genre": "판타지/SF"
    },
    {
      "title": "카구야 님은 고백받고 싶어 20권",
      "link": "https://ridibooks.com/books/1019062518?_rdt_sid=new-release&_rdt_idx=1",
      "author": "아카사카 아카",
      "genre": "학원"
    },
    {
      "title": "카구야님을 이야기하고 싶어 3권",
      "link": "https://ridibooks.com/books/1019062514?_rdt_sid=new-release&_rdt_idx=2",
      "author": "G3이다",
      "genre": "학원"
    },
    {
      "title": "철야의 노래 7권",
      "link": "https://ridibooks.com/books/1019062520?_rdt_sid=new-release&_rdt_idx=3",
      "author": "코토야마",
      "genre": "판타지/SF"
    },
    {
      "title": "마슐 5권",
      "link": "https://ridibooks.com/books/1019062519?_rdt_sid=new-release&_rdt_idx=4",
      "author": "코모토 하지메",
      "genre": "판타지/SF"
    },
    {
      "title": "내가 사랑 따위 하지 않아도 6권",
      "link": "https://ridibooks.com/books/1019062508?_rdt_sid=new-release&_rdt_idx=5",
      "author": "카즈이 카즈미",
      "genre": "해외 순정"
    },
    {
      "title": "좀100 -좀비가 되기 전에 하고 싶은 100가지- 3권",
      "link": "https://ridibooks.com/books/1019062511?_rdt_sid=new-release&_rdt_idx=6",
      "author": "타카타 코타로",
      "genre": "판타지/SF"
    },
    {
      "title": "녹아내려! 미조레짱 6권 (완결)",
      "link": "https://ridibooks.com/books/1019062517?_rdt_sid=new-release&_rdt_idx=7",
      "author": "타비 하나오",
      "genre": "코믹"
    },
    {
      "title": "장난을 잘 치는 타카기 양 16권",
      "link": "https://ridibooks.com/books/1019062521?_rdt_sid=new-release&_rdt_idx=8",
      "author": "야마모토 소이치로",
      "genre": "학원"
    },
    {
      "title": "아마노 메구미는 빈틈투성이! 24권",
      "link": "https://ridibooks.com/books/1019062522?_rdt_sid=new-release&_rdt_idx=9",
      "author": "네코구치",
      "genre": "학원"
    },
    {
      "title": "우리는 공부를 못해 18권",
      "link": "https://ridibooks.com/books/1019062523?_rdt_sid=new-release&_rdt_idx=10",
      "author": "츠츠이 타이시",
      "genre": "학원"
    },
    {
      "title": "14세의 사랑 9권",
      "link": "https://ridibooks.com/books/297043097?_rdt_sid=new-release&_rdt_idx=11",
      "author": "미즈타니 후카",
      "genre": "학원"
    },
    {
      "title": "이 흉애는 재앙입니다 2권",
      "link": "https://ridibooks.com/books/297043101?_rdt_sid=new-release&_rdt_idx=12",
      "author": "유메키 미츠루",
      "genre": "해외 순정"
    },
    {
      "title": "당신에게 바치는 붉은 장미 2권 (완결)",
      "link": "https://ridibooks.com/books/3010009128?_rdt_sid=new-release&_rdt_idx=13",
      "author": "이치 멜카",
      "genre": "드라마"
    },
    {
      "title": "저주받은 아이라 불리운 소환사 3권",
      "link": "https://ridibooks.com/books/806007982?_rdt_sid=new-release&_rdt_idx=14",
      "author": "코이시",
      "genre": "판타지/SF"
    },
    {
      "title": "그래도 남자는 믿지 않습니다 2권",
      "link": "https://ridibooks.com/books/806007984?_rdt_sid=new-release&_rdt_idx=15",
      "author": "아키야마 카오리",
      "genre": "해외 순정"
    },
    {
      "title": "[코믹] 데스마치에서 시작되는 이세계 광상곡 11권",
      "link": "https://ridibooks.com/books/777096835?_rdt_sid=new-release&_rdt_idx=16",
      "author": "아야 메구무",
      "genre": "판타지/SF"
    },
    {
      "title": "[코믹] 왕녀 전하는 화가 나셨나 봅니다 3권",
      "link": "https://ridibooks.com/books/777096842?_rdt_sid=new-release&_rdt_idx=17",
      "author": "요츠바 네코",
      "genre": "판타지/SF"
    },
    {
      "title": "9월의 사랑과 만나기까지 上",
      "link": "https://ridibooks.com/books/806007980?_rdt_sid=new-release&_rdt_idx=18",
      "author": "스가타 우리",
      "genre": "해외 순정"
    },
    {
      "title": "[마블] 어메이징 스파이더맨: 프레시 스타트 Vol. 3 - 헌티드 (완결)",
      "link": "https://ridibooks.com/books/862001640?_rdt_sid=new-release&_rdt_idx=19",
      "author": "닉 스펜서",
      "genre": "판타지/SF"
    }
  ]
}
