{
  "books": [
    {
      "title": "이세계 삼촌 4권",
      "link": "https://ridibooks.com/books/1690000863",
      "author": "호톤도 신데이루",
      "genre": "판타지/SF"
    },
    {
      "title": "에미야 가의 오늘의 밥상 5권",
      "link": "https://ridibooks.com/books/1690000861",
      "author": "TAa",
      "genre": "드라마"
    },
    {
      "title": "보이는 여고생 3권",
      "link": "https://ridibooks.com/books/1690000858",
      "author": "이즈미 토모키",
      "genre": "공포/추리"
    },
    {
      "title": "고래의 아이들은 모래 위에서 노래한다 11권",
      "link": "https://ridibooks.com/books/1690000856",
      "author": "우메다 아비",
      "genre": "판타지/SF"
    },
    {
      "title": "산과 식욕과 나 6권",
      "link": "https://ridibooks.com/books/1690000859",
      "author": "시나노가와 히데오",
      "genre": "코믹"
    },
    {
      "title": "[코믹] 방패 용사 성공담 11권",
      "link": "https://ridibooks.com/books/1690000857",
      "author": "아이야 큐",
      "genre": "판타지/SF"
    },
    {
      "title": "절대야망 10권",
      "link": "https://ridibooks.com/books/1603052502",
      "author": "조명운",
      "genre": "액션"
    },
    {
      "title": "앨리스와 조로쿠 8권",
      "link": "https://ridibooks.com/books/1690000860",
      "author": "이마이 테츠야",
      "genre": "판타지/SF"
    },
    {
      "title": "[코믹] 예를 들어 라스트 던전 앞 마을의 소년이 초반 마을에서 사는 듯한 이야기 3권",
      "link": "https://ridibooks.com/books/1690000862",
      "author": "후세마치 하지메",
      "genre": "판타지/SF"
    },
    {
      "title": "시가렛 & 체리 7권",
      "link": "https://ridibooks.com/books/806006428",
      "author": "카와카미 다이시로",
      "genre": "해외 순정"
    },
    {
      "title": "쿠로사키 말 따위 안 들을 거야 16권",
      "link": "https://ridibooks.com/books/505026298",
      "author": "마키노",
      "genre": "해외 순정"
    },
    {
      "title": "인간 외 CP 카탈로그 3권 (완결)",
      "link": "https://ridibooks.com/books/297033861",
      "author": "사사키 아오코",
      "genre": "드라마"
    },
    {
      "title": "유라쿠초 도깨비 과자점 3권",
      "link": "https://ridibooks.com/books/297033923",
      "author": "아스카 사츠키",
      "genre": "판타지/SF"
    },
    {
      "title": "[할리퀸] 다시 시작하는 새벽",
      "link": "https://ridibooks.com/books/1458005321",
      "author": "아이 마리토",
      "genre": "할리퀸"
    },
    {
      "title": "다이아몬드 에이스 actⅡ 21권",
      "link": "https://ridibooks.com/books/505026303",
      "author": "테라지마 유지",
      "genre": "스포츠"
    },
    {
      "title": "타카네와 하나 15권",
      "link": "https://ridibooks.com/books/505026279",
      "author": "시와스 유키",
      "genre": "해외 순정"
    },
    {
      "title": "모모치네 집 요괴 왕자 16권 (완결)",
      "link": "https://ridibooks.com/books/2007002726",
      "author": "쇼우토 아야",
      "genre": "판타지/SF"
    },
    {
      "title": "가정마도사의 이세계 생활 2권",
      "link": "https://ridibooks.com/books/3010004076",
      "author": "오노 아키히토",
      "genre": "드라마"
    },
    {
      "title": "티 선생님 7권 (완결)",
      "link": "https://ridibooks.com/books/2007002728",
      "author": "유쿠에 타카나",
      "genre": "드라마"
    },
    {
      "title": "여기예요! 경찰 오빠 5권",
      "link": "https://ridibooks.com/books/806006435",
      "author": "카라케미",
      "genre": "드라마"
    }
  ]
}
