{
  "books": [
    {
      "title": "이세계에서 슬로 라이프를(희망) 2권",
      "link": "https://ridibooks.com/books/3010004073",
      "author": "나가요리",
      "genre": "판타지/SF"
    },
    {
      "title": "여친, 빌리겠습니다 10권",
      "link": "https://ridibooks.com/books/505026234",
      "author": "미야지마 레이지",
      "genre": "해외 순정"
    },
    {
      "title": "선배! 지금부터 고백합니다! 4권",
      "link": "https://ridibooks.com/books/505026235",
      "author": "신모토 신",
      "genre": "해외 순정"
    },
    {
      "title": "사랑에 빠진 일진녀 5권 (완결)",
      "link": "https://ridibooks.com/books/806006417",
      "author": "오리하라 사치코",
      "genre": "드라마"
    },
    {
      "title": "칼바니아 이야기 19권",
      "link": "https://ridibooks.com/books/845022295",
      "author": "TONO",
      "genre": "해외 순정"
    },
    {
      "title": "Q.E.D. iff -증명종료- (큐이디 이프) 12권",
      "link": "https://ridibooks.com/books/505026055",
      "author": "카토우 모토히로",
      "genre": "공포/추리"
    },
    {
      "title": "C.M.B. 박물관 사건목록(씨엠비) 40권",
      "link": "https://ridibooks.com/books/505026054",
      "author": "카토우 모토히로",
      "genre": "학원"
    },
    {
      "title": "추락 여고생과 폐인 교사 7권",
      "link": "https://ridibooks.com/books/505026051",
      "author": "sora",
      "genre": "해외 순정"
    },
    {
      "title": "푸른 하늘 흐린 하늘 2권",
      "link": "https://ridibooks.com/books/2066001563",
      "author": "loundraw",
      "genre": "드라마"
    },
    {
      "title": "오컬트 짱은 말할 수 없어 3권",
      "link": "https://ridibooks.com/books/297033828",
      "author": "혼다 하지메",
      "genre": "코믹"
    },
    {
      "title": "죽음의 법칙 [개정판] 10권",
      "link": "https://ridibooks.com/books/1603052441",
      "author": "고행석",
      "genre": "액션"
    },
    {
      "title": "공정 드래곤즈 9권",
      "link": "https://ridibooks.com/books/297033825",
      "author": "쿠와바라 타쿠",
      "genre": "판타지/SF"
    },
    {
      "title": "카이니스의 황금새 3권",
      "link": "https://ridibooks.com/books/3010004066",
      "author": "하타 카즈키",
      "genre": "드라마"
    },
    {
      "title": "호시노, 눈을 감아. 12권",
      "link": "https://ridibooks.com/books/505026056",
      "author": "나가시이 코헤이",
      "genre": "해외 순정"
    },
    {
      "title": "우리들은 미쳤다 12권",
      "link": "https://ridibooks.com/books/297033781",
      "author": "안도 나츠미",
      "genre": "해외 순정"
    },
    {
      "title": "절벽 위의 란 5권",
      "link": "https://ridibooks.com/books/297033782",
      "author": "암미츠",
      "genre": "해외 순정"
    },
    {
      "title": "절대가련 칠드런 58권",
      "link": "https://ridibooks.com/books/1019035298",
      "author": "시이나 타카시",
      "genre": "판타지/SF"
    },
    {
      "title": "드래곤볼 슈퍼 13권",
      "link": "https://ridibooks.com/books/1019033087",
      "author": "토요타로",
      "genre": "판타지/SF"
    },
    {
      "title": "컴온 어 마이 하우스 2권",
      "link": "https://ridibooks.com/books/297033767",
      "author": "난바 아츠코",
      "genre": "해외 순정"
    },
    {
      "title": "다정마무정협 10권",
      "link": "https://ridibooks.com/books/1603052428",
      "author": "천제황",
      "genre": "무협"
    }
  ]
}
