{
  "books": [
    {
      "title": "지박소년 하나코 군 18권",
      "link": "https://ridibooks.com/books/845035319?_rdt_sid=new_release&_rdt_idx=0",
      "author": "아이다 이로",
      "genre": "판타지/SF"
    },
    {
      "title": "여성향 게임 속에서 내가 히로인이자 구세주?! 4권",
      "link": "https://ridibooks.com/books/505068024?_rdt_sid=new_release&_rdt_idx=1",
      "author": "츠지모토 유",
      "genre": "판타지/SF"
    },
    {
      "title": "마법사의 신부 16권",
      "link": "https://ridibooks.com/books/505067858?_rdt_sid=new_release&_rdt_idx=2",
      "author": "야마자키 코레",
      "genre": "드라마"
    },
    {
      "title": "도쿄 에일리언즈 4권",
      "link": "https://ridibooks.com/books/845035320?_rdt_sid=new_release&_rdt_idx=3",
      "author": "NAOE",
      "genre": "판타지/SF"
    },
    {
      "title": "이세계 약국 8권",
      "link": "https://ridibooks.com/books/297053328?_rdt_sid=new_release&_rdt_idx=4",
      "author": "타카노 세이",
      "genre": "판타지/SF"
    },
    {
      "title": "이세계 주점 노부 14권",
      "link": "https://ridibooks.com/books/297053335?_rdt_sid=new_release&_rdt_idx=5",
      "author": "버지니아 이등병",
      "genre": "판타지/SF"
    },
    {
      "title": "바깥 나라의 소녀 dear. (외전) (완결)",
      "link": "https://ridibooks.com/books/505067857?_rdt_sid=new_release&_rdt_idx=6",
      "author": "나가베",
      "genre": "드라마"
    },
    {
      "title": "폭설 속의 불청객 10권 (완결)",
      "link": "https://ridibooks.com/books/1603057389?_rdt_sid=new_release&_rdt_idx=7",
      "author": "고행석",
      "genre": "액션"
    },
    {
      "title": "챔프D 224호(2023.01.15)",
      "link": "https://ridibooks.com/books/847004526?_rdt_sid=new_release&_rdt_idx=8",
      "author": "챔프D 편집부",
      "genre": "만화잡지"
    },
    {
      "title": "아가씨와 충견군 3권",
      "link": "https://ridibooks.com/books/505067854?_rdt_sid=new_release&_rdt_idx=9",
      "author": "하츠하루",
      "genre": "해외 순정"
    },
    {
      "title": "킹덤 65권",
      "link": "https://ridibooks.com/books/1019075631?_rdt_sid=new_release&_rdt_idx=10",
      "author": "하라 야스히사",
      "genre": "무협"
    },
    {
      "title": "카구야 님은 고백받고 싶어 25권",
      "link": "https://ridibooks.com/books/1019075634?_rdt_sid=new_release&_rdt_idx=11",
      "author": "아카사카 아카",
      "genre": "학원"
    },
    {
      "title": "더 화이팅 신장재편판 28권",
      "link": "https://ridibooks.com/books/505067837?_rdt_sid=new_release&_rdt_idx=12",
      "author": "모리카와 죠지",
      "genre": "스포츠"
    },
    {
      "title": "쿠보 양은 나를 내버려 두지 않아 9권",
      "link": "https://ridibooks.com/books/1019075635?_rdt_sid=new_release&_rdt_idx=13",
      "author": "유키모리 네네",
      "genre": "해외 순정"
    },
    {
      "title": "허니 레몬 소다 19권",
      "link": "https://ridibooks.com/books/1019075633?_rdt_sid=new_release&_rdt_idx=14",
      "author": "무라타 마유",
      "genre": "해외 순정"
    },
    {
      "title": "추방자들의 밤 5권",
      "link": "https://ridibooks.com/books/1019075624?_rdt_sid=new_release&_rdt_idx=15",
      "author": "호시노 마코토",
      "genre": "판타지/SF"
    },
    {
      "title": "그런데 치기라 군이 너무 달콤해. 7권",
      "link": "https://ridibooks.com/books/297053161?_rdt_sid=new_release&_rdt_idx=16",
      "author": "아난 쿠지라",
      "genre": "해외 순정"
    },
    {
      "title": "요괴야화담 9권",
      "link": "https://ridibooks.com/books/297053317?_rdt_sid=new_release&_rdt_idx=17",
      "author": "마츠리",
      "genre": "판타지/SF"
    },
    {
      "title": "송혼의 소녀와 장례여행 7권 (완결)",
      "link": "https://ridibooks.com/books/297053318?_rdt_sid=new_release&_rdt_idx=18",
      "author": "로나",
      "genre": "판타지/SF"
    },
    {
      "title": "분명 사랑이니까 필요 없어 4권",
      "link": "https://ridibooks.com/books/1019075619?_rdt_sid=new_release&_rdt_idx=19",
      "author": "미나세 아이",
      "genre": "해외 순정"
    }
  ]
}
